CGS.py
crawl_only.py
scrapy.cfg
ComicSpider/__init__.py
ComicSpider/items.py
ComicSpider/middlewares.py
ComicSpider/pipelines.py
ComicSpider/settings.py
ComicSpider/spiders/__init__.py
ComicSpider/spiders/basecomicspider.py
ComicSpider/spiders/ehentai.py
ComicSpider/spiders/hitomi.py
ComicSpider/spiders/jm.py
ComicSpider/spiders/kaobei.py
ComicSpider/spiders/mangabz.py
ComicSpider/spiders/wnacg.py
GUI/__init__.py
GUI/browser_window.py
GUI/conf_dialog.py
GUI/gui.py
GUI/mainwindow.py
GUI/core/__init__.py
GUI/core/font.py
GUI/core/theme.py
GUI/manager/__init__.py
GUI/manager/ags.py
GUI/manager/async_task.py
GUI/manager/clip.py
GUI/manager/preprocess.py
GUI/script/__init__.py
GUI/script/kemono.py
GUI/src/__init__.py
GUI/src/material_ct.py
GUI/src/preview_format/ags.js
GUI/src/preview_format/bootstrap.min.css
GUI/src/preview_format/bootstrap.min.js
GUI/src/preview_format/clip.js
GUI/src/preview_format/index.html
GUI/src/preview_format/index_ags.html
GUI/src/preview_format/index_by_clip.html
GUI/src/preview_format/public.css
GUI/src/preview_format/public.js
GUI/src/preview_format/public_clip.css
GUI/src/preview_format/tasks_extend.js
GUI/src/preview_format/tips.js
GUI/thread/__init__.py
GUI/thread/ags.py
GUI/tools/__init__.py
GUI/tools/ags.py
GUI/tools/chore.py
GUI/tools/domain.py
GUI/tools/hitomi_tool.py
GUI/tools/rv_tool.py
GUI/tools/status.py
GUI/uic/__init__.py
GUI/uic/browser.py
GUI/uic/conf_dia.py
GUI/uic/ui_mainwindow.py
GUI/uic/qfluent/__init__.py
GUI/uic/qfluent/patch_uic.py
GUI/uic/qfluent/components/__init__.py
GUI/uic/qfluent/components/cust.py
GUI/uic/qfluent/components/splash_screen.py
GUI/uic/qfluent/components/text_componet.py
GUI/uic/qfluent/components/updater.py
assets/__init__.py
assets/conf_sample.yml
assets/conf_sample_script.yml
assets/config_icon.png
assets/github_format.html
assets/pubilsh_helper.html
assets/update.txt
assets/res/__init__.py
assets/res/transfer.py
assets/res/locale/en_US.yml
assets/res/locale/zh_CN.yml
custom/__init__.py
comicguispider-2.7.2.dist-info/METADATA
comicguispider-2.7.2.dist-info/WHEEL
comicguispider-2.7.2.dist-info/entry_points.txt
comicguispider-2.7.2.dist-info/licenses/LICENSE
comicguispider-2.7.2.dist-info/RECORD
