Metadata-Version: 2.4
Name: ComicGUISpider
Version: 2.7.2
Summary: GUI Comic Downloader
Project-URL: Repository, https://github.com/jasoneri/ComicGUISpider
Project-URL: Documentation, https://doc.comicguispider.nyc.mn/
Project-URL: Changelog, https://doc.comicguispider.nyc.mn/changelog/history
Project-URL: Releases, https://github.com/jasoneri/ComicGUISpider/releases
Author-email: jsoneri <jsoneri@outlook.com>
License-File: LICENSE
Keywords: comic,downloader,gui,spider
Classifier: Development Status :: 4 - Beta
Classifier: Intended Audience :: End Users/Desktop
Classifier: License :: OSI Approved :: MIT License
Classifier: Programming Language :: Python :: 3.12
Requires-Python: <3.14,>=3.12
Requires-Dist: aiofiles
Requires-Dist: brotli
Requires-Dist: colorama
Requires-Dist: h11>=0.16.0
Requires-Dist: httpx[http2]
Requires-Dist: jsonpath-rw
Requires-Dist: loguru
Requires-Dist: lxml
Requires-Dist: markdown
Requires-Dist: pillow-avif-plugin
Requires-Dist: pillow>=11.3.0
Requires-Dist: polib
Requires-Dist: psutil
Requires-Dist: pyexecjs
Requires-Dist: pyqt-fluent-widgets
Requires-Dist: pyqt5
Requires-Dist: pyqt5-qt5==5.15.2; platform_system == 'Windows'
Requires-Dist: pyqtwebengine
Requires-Dist: pyqtwebengine-qt5==5.15.2; platform_system == 'Windows'
Requires-Dist: pyyaml
Requires-Dist: requests>=2.32.4
Requires-Dist: scrapy>=2.13.0
Requires-Dist: setuptools>=78.1.1
Requires-Dist: tqdm
Requires-Dist: uncurl
Requires-Dist: urllib3>=2.5.0
Requires-Dist: uv
Provides-Extra: script
Requires-Dist: pandas; extra == 'script'
Requires-Dist: redis; extra == 'script'
